LICENSE
MANIFEST.in
README.md
setup.py
discoart/__init__.py
discoart/__main__.py
discoart/api.py
discoart/config.py
discoart/create.py
discoart/executors.py
discoart/helper.py
discoart/parser.py
discoart/persist.py
discoart/prompt.py
discoart/runner.py
discoart/nn/__init__.py
discoart/nn/losses.py
discoart/nn/make_cutouts.py
discoart/nn/perlin_noises.py
discoart/nn/sec_diff.py
discoart/nn/transform.py
discoart/resources/cut-schedules.yml
discoart/resources/default.yml
discoart/resources/docstrings.yml
discoart/resources/flow.yml
discoart/resources/models.yml
discoart/resources/vocab.txt
stable_diffusion.egg-info/PKG-INFO
stable_diffusion.egg-info/SOURCES.txt
stable_diffusion.egg-info/dependency_links.txt
stable_diffusion.egg-info/not-zip-safe
stable_diffusion.egg-info/requires.txt
stable_diffusion.egg-info/top_level.txt