Metadata-Version: 2.1
Name: stable-diffusion
Version: 0.0.0
Summary: Create Disco Diffusion artworks in one line
Home-page: https://github.com/jina-ai/discoart
Author: Jina AI
Author-email: hello@jina.ai
License: MIT
Download-URL: https://github.com/jina-ai/discoart/tags
Project-URL: Source, https://github.com/jina-ai/discoart/
Project-URL: Tracker, https://github.com/jina-ai/discoart/issues
Keywords: discoart diffusion art dalle disco-diffusion generative-art creative-ai cross-modal multi-modal artwork
Platform: UNKNOWN
Classifier: Development Status :: 5 - Production/Stable
Classifier: Intended Audience :: Developers
Classifier: Intended Audience :: Education
Classifier: Intended Audience :: Science/Research
Classifier: Programming Language :: Python :: 3.7
Classifier: Programming Language :: Python :: 3.8
Classifier: Programming Language :: Python :: 3.9
Classifier: Programming Language :: Python :: 3.10
Classifier: Programming Language :: Unix Shell
Classifier: Environment :: Console
Classifier: License :: OSI Approved :: Apache Software License
Classifier: Operating System :: OS Independent
Classifier: Topic :: Database :: Database Engines/Servers
Classifier: Topic :: Scientific/Engineering :: Artificial Intelligence
Classifier: Topic :: Internet :: WWW/HTTP :: Indexing/Search
Classifier: Topic :: Scientific/Engineering :: Image Recognition
Classifier: Topic :: Multimedia :: Video
Classifier: Topic :: Scientific/Engineering
Classifier: Topic :: Scientific/Engineering :: Mathematics
Classifier: Topic :: Software Development
Classifier: Topic :: Software Development :: Libraries
Classifier: Topic :: Software Development :: Libraries :: Python Modules
Provides-Extra: test
